fds/__init__.py
fds/sdk/__init__.py
fds/sdk/SecurityExplanation/__init__.py
fds/sdk/SecurityExplanation/api_client.py
fds/sdk/SecurityExplanation/configuration.py
fds/sdk/SecurityExplanation/exceptions.py
fds/sdk/SecurityExplanation/model_utils.py
fds/sdk/SecurityExplanation/rest.py
fds/sdk/SecurityExplanation/api/__init__.py
fds/sdk/SecurityExplanation/api/security_explanation_api.py
fds/sdk/SecurityExplanation/apis/__init__.py
fds/sdk/SecurityExplanation/model/__init__.py
fds/sdk/SecurityExplanation/model/api_client_error_response.py
fds/sdk/SecurityExplanation/model/api_error.py
fds/sdk/SecurityExplanation/model/broker_research_summary.py
fds/sdk/SecurityExplanation/model/error_source.py
fds/sdk/SecurityExplanation/model/explanation_create_response.py
fds/sdk/SecurityExplanation/model/explanation_create_response_root.py
fds/sdk/SecurityExplanation/model/explanation_status.py
fds/sdk/SecurityExplanation/model/explanation_status_root.py
fds/sdk/SecurityExplanation/model/security_explanation_parameters_root.py
fds/sdk/SecurityExplanation/model/security_explanation_request_parameters.py
fds/sdk/SecurityExplanation/model/security_explanation_response.py
fds/sdk/SecurityExplanation/model/security_explanation_response_root.py
fds/sdk/SecurityExplanation/models/__init__.py
fds_sdk_securityexplanation-2.2.0.dist-info/licenses/LICENSE
fds_sdk_securityexplanation-2.2.0.dist-info/METADATA
fds_sdk_securityexplanation-2.2.0.dist-info/WHEEL
fds_sdk_securityexplanation-2.2.0.dist-info/top_level.txt
fds_sdk_securityexplanation-2.2.0.dist-info/RECORD
